<Settings>
  <Sitecore>
    <XConnect>
      <Services>
        <XConnect.Client.Configuration>
          <Options>
            <Models>
              <CinemaDetailsCollectionModel>
                <TypeName>LearnEXM.Foundation.CollectionModel.Builder.Models.CollectionModels.CinemaDetailsCollectionModel, LearnEXM.Foundation.CollectionModel.Builder</TypeName>
              </CinemaDetailsCollectionModel>
            </Models>
          </Options>
        </XConnect.Client.Configuration>
      </Services>
    </XConnect>
  </Sitecore>
</Settings>